{"version": "4.6.0", "flags": {}, "shapes": [{"label": "building", "points": [[200.84626234132583, 69.95768688293371], [201.41043723554301, 75.17630465444287], [208.0394922425952, 74.61212976022567], [208.0394922425952, 69.95768688293371]], "group_id": null, "shape_type": "polygon", "flags": {}}, {"label": "building", "points": [[195.6, 80.4], [196.0, 89.6], [203.5, 88.9], [203.2, 80.6]], "group_id": null, "shape_type": "polygon", "flags": {}}, {"label": "building", "points": [[175.5, 96.6], [177.1, 105.6], [181.3, 104.9], [181.3, 96.1]], "group_id": null, "shape_type": "polygon", "flags": {}}, {"label": "building", "points": [[170.4, 106.5], [170.7, 113.7], [176.5, 113.4], [176.3, 106.7]], "group_id": null, "shape_type": "polygon", "flags": {}}, {"label": "building", "points": [[159.5, 98.5], [159.5, 104.4], [165.2, 104.2], [165.1, 98.7]], "group_id": null, "shape_type": "polygon", "flags": {}}, {"label": "building", "points": [[153.7, 105.0], [153.5, 113.9], [159.9, 113.9], [159.9, 105.0]], "group_id": null, "shape_type": "polygon", "flags": {}}, {"label": "building", "points": [[211.8, 117.5], [211.8, 124.9], [217.2, 125.1], [217.2, 117.7]], "group_id": null, "shape_type": "polygon", "flags": {}}, {"label": "building", "points": [[230.7, 116.6], [230.8, 122.3], [236.5, 122.3], [236.7, 116.9]], "group_id": null, "shape_type": "polygon", "flags": {}}, {"label": "building", "points": [[190.1, 88.3], [184.1, 91.8], [187.1, 96.0], [192.7, 92.3]], "group_id": null, "shape_type": "polygon", "flags": {}}, {"label": "building", "points": [[181.3, 74.4], [181.5, 81.4], [187.3, 81.3], [187.2, 74.4]], "group_id": null, "shape_type": "polygon", "flags": {}}, {"label": "building", "points": [[196.6, 94.5], [196.5, 99.1], [205.1, 98.9], [205.1, 94.6]], "group_id": null, "shape_type": "polygon", "flags": {}}, {"label": "building", "points": [[192.3, 107.3], [190.6, 113.2], [195.9, 113.3], [196.4, 108.1]], "group_id": null, "shape_type": "polygon", "flags": {}}, {"label": "building", "points": [[189.0, 112.7], [186.7, 120.1], [191.8, 121.1], [193.8, 113.6]], "group_id": null, "shape_type": "polygon", "flags": {}}, {"label": "building", "points": [[194.5, 117.5], [194.6, 125.4], [201.2, 125.3], [201.1, 117.6]], "group_id": null, "shape_type": "polygon", "flags": {}}, {"label": "building", "points": [[201.5, 112.2], [201.3, 117.3], [210.2, 117.3], [210.2, 112.4]], "group_id": null, "shape_type": "polygon", "flags": {}}, {"label": "building", "points": [[214.4, 106.5], [214.4, 113.5], [221.0, 113.6], [221.0, 106.1]], "group_id": null, "shape_type": "polygon", "flags": {}}, {"label": "building", "points": [[208.4, 93.0], [208.7, 99.2], [213.2, 99.0], [213.3, 92.8]], "group_id": null, "shape_type": "polygon", "flags": {}}, {"label": "building", "points": [[159.4, 113.6], [159.1, 120.9], [164.9, 121.0], [165.1, 113.6]], "group_id": null, "shape_type": "polygon", "flags": {}}, {"label": "building", "points": [[364.6090534979424, 26.611796982167352], [357.61316872427983, 31.001371742112482], [358.0246913580247, 36.351165980795614], [366, 32], [366, 29]], "group_id": null, "shape_type": "polygon", "flags": {}}, {"label": "building", "points": [[180.7, 91.1], [175.1, 91.2], [175.2, 94.8], [180.5, 94.5]], "group_id": null, "shape_type": "polygon", "flags": {}}], "imagePath": "d94.tif", "imageHeight": 274, "imageWidth": 367}