{"version": "4.6.0", "flags": {}, "shapes": [{"label": "building", "points": [[136.8, 139.7], [127.3, 142.0], [128.6, 150.6], [142.29651162790697, 148.9825581395349]], "group_id": null, "shape_type": "polygon", "flags": {}}, {"label": "building", "points": [[115.8, 148.9], [110.4, 151.2], [112.6, 158.3], [119.1, 156.5]], "group_id": null, "shape_type": "polygon", "flags": {}}, {"label": "building", "points": [[237.8, 164.7], [238.1, 178.9], [244.3, 178.6], [243.8, 164.5]], "group_id": null, "shape_type": "polygon", "flags": {}}, {"label": "building", "points": [[255.2, 149.7], [251.1, 153.2], [256.8, 157.6], [257.5, 152.6]], "group_id": null, "shape_type": "polygon", "flags": {}}, {"label": "building", "points": [[250.6, 158.9], [250.5, 162.3], [255.7, 162.2], [255.6, 159.1]], "group_id": null, "shape_type": "polygon", "flags": {}}, {"label": "building", "points": [[284.4, 163.2], [280.4, 163.5], [280.8, 171.1], [286.9, 170.6]], "group_id": null, "shape_type": "polygon", "flags": {}}, {"label": "building", "points": [[285.5, 170.6], [280.8, 171.1], [281.1, 175.5], [286.1, 175.4]], "group_id": null, "shape_type": "polygon", "flags": {}}, {"label": "building", "points": [[301.7, 140.5], [296.9, 143.0], [305.1, 155.2], [312.3, 148.5]], "group_id": null, "shape_type": "polygon", "flags": {}}, {"label": "building", "points": [[308.0, 259.0], [297.1, 265.9], [301.7, 269.6], [307.0, 266.3], [310.0, 268.4], [314.8, 265.3]], "group_id": null, "shape_type": "polygon", "flags": {}}, {"label": "building", "points": [[288.3, 263.2], [283.3, 267.5], [289.9, 273.6], [294.6, 268.8]], "group_id": null, "shape_type": "polygon", "flags": {}}, {"label": "building", "points": [[293.6, 269.2], [290.4, 272.8], [297.2, 284.0], [300.1, 282.5], [298.1, 275.3]], "group_id": null, "shape_type": "polygon", "flags": {}}, {"label": "building", "points": [[283.4, 280.2], [278.2, 282.8], [281.7, 289.3], [288.2, 285.6]], "group_id": null, "shape_type": "polygon", "flags": {}}, {"label": "building", "points": [[269.4, 239.8], [259.3, 240.5], [263.6, 254.6], [268.6, 256.7]], "group_id": null, "shape_type": "polygon", "flags": {}}, {"label": "building", "points": [[241.6, 306.4], [241.4, 312.1], [246.6, 312.3], [246.8, 306.6]], "group_id": null, "shape_type": "polygon", "flags": {}}, {"label": "building", "points": [[244.5, 316.6], [240.7, 319.0], [245.9, 325.3], [249.2, 323.0]], "group_id": null, "shape_type": "polygon", "flags": {}}, {"label": "building", "points": [[263.5, 330.3], [261.8, 332.3], [269.0, 338.2], [271.1, 335.7], [268.3, 330.8]], "group_id": null, "shape_type": "polygon", "flags": {}}, {"label": "building", "points": [[311.7, 320.0], [306.3, 320.3], [306.6, 328.6], [313.5, 328.7], [313.5, 325.4]], "group_id": null, "shape_type": "polygon", "flags": {}}, {"label": "building", "points": [[321.0, 339.1], [312.7, 338.8], [312.5, 343.6], [321.5, 343.6]], "group_id": null, "shape_type": "polygon", "flags": {}}, {"label": "building", "points": [[318.7, 346.4], [313.4, 348.3], [316.0, 352.8], [328.6, 350.7], [328.3, 346.4]], "group_id": null, "shape_type": "polygon", "flags": {}}, {"label": "building", "points": [[350.5, 347.3], [344.9, 350.7], [349.1, 356.2], [354.2, 351.5]], "group_id": null, "shape_type": "polygon", "flags": {}}], "imagePath": "j211.tif", "imageHeight": 439, "imageWidth": 674}